querier/__init__.py
querier/datasets/__init__.py
querier/datasets/download.py
querier/queries/__init__.py
querier/queries/concat.py
querier/queries/delete.py
querier/queries/drop.py
querier/queries/filtr.py
querier/queries/join.py
querier/queries/request.py
querier/queries/select.py
querier/queries/set.py
querier/queries/summarize.py
querier/queries/update.py
querier/tests/__init__.py
querier/tests/tests_concat.py
querier/tests/tests_delete.py
querier/tests/tests_drop.py
querier/tests/tests_filtr.py
querier/tests/tests_join.py
querier/tests/tests_request.py
querier/tests/tests_select.py
querier/tests/tests_summarize.py
querier/tests/tests_update.py
querier/utils/__init__.py
querier/utils/convert.py
querier/utils/deepcopy.py
querier/utils/memoize.py
querier/utils/parse_request.py
querier/wrapper/__init__.py
querier/wrapper/wrapper.py
querier-0.5.0.dist-info/LICENSE
querier-0.5.0.dist-info/METADATA
querier-0.5.0.dist-info/WHEEL
querier-0.5.0.dist-info/top_level.txt
querier-0.5.0.dist-info/RECORD
